amplitude_sdk/__init__.py
amplitude_sdk/clients.py
amplitude_sdk-1.0.4.dist-info/LICENSE
amplitude_sdk-1.0.4.dist-info/METADATA
amplitude_sdk-1.0.4.dist-info/WHEEL
amplitude_sdk-1.0.4.dist-info/top_level.txt
amplitude_sdk-1.0.4.dist-info/RECORD
