Metadata-Version: 2.1
Name: amplitude-sdk
Version: 1.0.4
Summary: Amplitude Python 3 SDK.
Home-page: https://github.com/paulokuong/amplitude
Author: Paulo Kuong
Author-email: UNKNOWN
License: MIT
Keywords: amplitude sdk Amplitude v2  bahav HTTP api V2 Batch Event Upload  Identify  Attribution  Behavioral Cohorts  Chart Annotations  Dashboard REST  Export  Group Identify  Releases  SCIM  Taxonomy  User Privacy  User Profile
Platform: UNKNOWN
